Workbook

Sheet raw_data
A1: OLD_DATE | B1: date | C1: merchant | D1: amount | E1: original_category | F1: my_category | G1: source | H1: notes
A2: 45694 | B2: =TEXT(A2,"yyyy-mm") -> 2025-02 | C2: JOHNNY DELMONICO'S | D2: 434.92 | E2: Restaurants | F2: {=IFERROR( INDEX(lookup_table!B:B, MATCH(TRUE, ISNUMBER(SEARCH(lookup_table!A:A,C2)), 0) ), "Uncategorized")} -> Dining Out | G2: Card1
A3: 45666 | B3: =TEXT(A3,"yyyy-mm") -> 2025-01 | C3: KWIK TRIP | D3: 8.31 | E3: Gas / Fuel | F3: {=IFERROR( INDEX(lookup_table!B:B, MATCH(TRUE, ISNUMBER(SEARCH(lookup_table!A:A,C3)), 0) ), "Uncategorized")} -> Transportation | G3: Bank2
A4: 45668 | B4: =TEXT(A4,"yyyy-mm") -> 2025-01 | C4: TARGET | D4: 6.33 | E4: Shopping | F4: {=IFERROR( INDEX(lookup_table!B:B, MATCH(TRUE, ISNUMBER(SEARCH(lookup_table!A:A,C4)), 0) ), "Uncategorized")} -> Groceries | G4: Bank2
A5: 45674 | B5: =TEXT(A5,"yyyy-mm") -> 2025-01 | C5: HAWKS BAR AND GRILL | D5: 5.16 | E5: Dining Out | F5: {=IFERROR( INDEX(lookup_table!B:B, MATCH(TRUE, ISNUMBER(SEARCH(lookup_table!A:A,C5)), 0) ), "Uncategorized")} -> Dining Out | G5: Bank2
A6: 45675 | B6: =TEXT(A6,"yyyy-mm") -> 2025-01 | C6: KWIK TRIP | D6: 5.93 | E6: Gas / Fuel | F6: {=IFERROR( INDEX(lookup_table!B:B, MATCH(TRUE, ISNUMBER(SEARCH(lookup_table!A:A,C6)), 0) ), "Uncategorized")} -> Transportation | G6: Bank2
A7: 45675 | B7: =TEXT(A7,"yyyy-mm") -> 2025-01 | C7: KWIK TRIP | D7: 4.21 | E7: Gas / Fuel | F7: {=IFERROR( INDEX(lookup_table!B:B, MATCH(TRUE, ISNUMBER(SEARCH(lookup_table!A:A,C7)), 0) ), "Uncategorized")} -> Transportation | G7: Bank2
A8: 45676 | B8: =TEXT(A8,"yyyy-mm") -> 2025-01 | C8: CANTEEN VENDING LAC | D8: 2.25 | E8: Dining Out | F8: {=IFERROR( INDEX(lookup_table!B:B, MATCH(TRUE, ISNUMBER(SEARCH(lookup_table!A:A,C8)), 0) ), "Uncategorized")} -> Other | G8: Bank2
A9: 45681 | B9: =TEXT(A9,"yyyy-mm") -> 2025-01 | C9: BP | D9: 6.52 | E9: Gas / Fuel | F9: {=IFERROR( INDEX(lookup_table!B:B, MATCH(TRUE, ISNUMBER(SEARCH(lookup_table!A:A,C9)), 0) ), "Uncategorized")} -> Transportation | G9: Bank2
A10: 45690 | B10: =TEXT(A10,"yyyy-mm") -> 2025-02 | C10: STARBUCKS | D10: 16.13 | E10: Restaurants | F10: {=IFERROR( INDEX(lookup_table!B:B, MATCH(TRUE, ISNUMBER(SEARCH(lookup_table!A:A,C10)), 0) ), "Uncategorized")} -> Dining Out | G10: Card2
A11: 45690 | B11: =TEXT(A11,"yyyy-mm") -> 2025-02 | C11: WALMART | D11: 74.42 | E11: Grocery | F11: {=IFERROR( INDEX(lookup_table!B:B, MATCH(TRUE, ISNUMBER(SEARCH(lookup_table!A:A,C11)), 0) ), "Uncategorized")} -> Groceries | G11: Card1
A12: 45690 | B12: =TEXT(A12,"yyyy-mm") -> 2025-02 | C12: AMAZON MKTPL | D12: 9.08 | E12: Merchandise | F12: {=IFERROR( INDEX(lookup_table!B:B, MATCH(TRUE, ISNUMBER(SEARCH(lookup_table!A:A,C12)), 0) ), "Uncategorized")} -> Shopping | G12: Card2
A13: 45690 | B13: =TEXT(A13,"yyyy-mm") -> 2025-02 | C13: KWIK TRIP | D13: 43.57 | E13: Gas | F13: {=IFERROR( INDEX(lookup_table!B:B, MATCH(TRUE, ISNUMBER(SEARCH(lookup_table!A:A,C13)), 0) ), "Uncategorized")} -> Transportation | G13: Card1
... A436: 45894 | B436: =TEXT(A436,"yyyy-mm") -> 2025-08 | C436: PARAMOUNT+ | D436: 4.74 | E436: Utilities | F436: {=IFERROR( INDEX(lookup_table!B:B, MATCH(TRUE, ISNUMBER(SEARCH(lookup_table!A:A,C436)), 0) ), "Uncategorized")} -> Subscriptions | G436: Card1
A437: 45894 | B437: =TEXT(A437,"yyyy-mm") -> 2025-08 | C437: 76 | D437: 15.12 | E437: Gas | F437: {=IFERROR( INDEX(lookup_table!B:B, MATCH(TRUE, ISNUMBER(SEARCH(lookup_table!A:A,C437)), 0) ), "Uncategorized")} -> Transportation | G437: Card1
A438: 45894 | B438: =TEXT(A438,"yyyy-mm") -> 2025-08 | C438: ASHFORD VALLEY STATE ROUTE US ASHFORD WA | D438: 4.99 | E438: Uncategorized | F438: {=IFERROR( INDEX(lookup_table!B:B, MATCH(TRUE, ISNUMBER(SEARCH(lookup_table!A:A,C438)), 0) ), "Uncategorized")} -> Transportation | G438: Bank2
A439: 45894 | B439: =TEXT(A439,"yyyy-mm") -> 2025-08 | C439: JACKSON VISITOR CENTER | D439: 11.88 | E439: Other | F439: {=IFERROR( INDEX(lookup_table!B:B, MATCH(TRUE, ISNUMBER(SEARCH(lookup_table!A:A,C439)), 0) ), "Uncategorized")} -> Travel | G439: Card1
A440: 45895 | B440: =TEXT(A440,"yyyy-mm") -> 2025-08 | C440: YAMATO SUSHI | D440: 23.2 | E440: Transportation | F440: {=IFERROR( INDEX(lookup_table!B:B, MATCH(TRUE, ISNUMBER(SEARCH(lookup_table!A:A,C440)), 0) ), "Uncategorized")} -> Dining Out | G440: Card1
A441: 45896 | B441: =TEXT(A441,"yyyy-mm") -> 2025-08 | C441: STATE FARM INSURANCE | D441: 59.86 | E441: Services | F441: {=IFERROR( INDEX(lookup_table!B:B, MATCH(TRUE, ISNUMBER(SEARCH(lookup_table!A:A,C441)), 0) ), "Uncategorized")} -> Bills | G441: Card2
A442: 45896 | B442: =TEXT(A442,"yyyy-mm") -> 2025-08 | C442: JUANITA'S MEXICAN | D442: 11.91 | E442: Entertainment | F442: {=IFERROR( INDEX(lookup_table!B:B, MATCH(TRUE, ISNUMBER(SEARCH(lookup_table!A:A,C442)), 0) ), "Uncategorized")} -> Dining Out | G442: Card1
A443: 45896 | B443: =TEXT(A443,"yyyy-mm") -> 2025-08 | C443: SOTTO NIGHT CLUB | D443: 5 | E443: Gasoline | F443: {=IFERROR( INDEX(lookup_table!B:B, MATCH(TRUE, ISNUMBER(SEARCH(lookup_table!A:A,C443)), 0) ), "Uncategorized")} -> Dining Out | G443: Card2
A444: 45896 | B444: =TEXT(A444,"yyyy-mm") -> 2025-08 | C444: TRADER JOES | D444: 36.12 | E444: Grocery | F444: {=IFERROR( INDEX(lookup_table!B:B, MATCH(TRUE, ISNUMBER(SEARCH(lookup_table!A:A,C444)), 0) ), "Uncategorized")} -> Groceries | G444: Card1
A445: 45896 | B445: =TEXT(A445,"yyyy-mm") -> 2025-08 | C445: TRADER JOES | D445: 8.27 | E445: Grocery | F445: {=IFERROR( INDEX(lookup_table!B:B, MATCH(TRUE, ISNUMBER(SEARCH(lookup_table!A:A,C445)), 0) ), "Uncategorized")} -> Groceries | G445: Card1
A446: 45896 | B446: =TEXT(A446,"yyyy-mm") -> 2025-08 | C446: SQ *FEIRO MARI 08/27/25 21:23 SQUARE PURCHASE PORT ANGELES WA | D446: 6.5 | E446: Uncategorized | F446: {=IFERROR( INDEX(lookup_table!B:B, MATCH(TRUE, ISNUMBER(SEARCH(lookup_table!A:A,C446)), 0) ), "Uncategorized")} -> Other | G446: Bank2
A447: 45896 | B447: =TEXT(A447,"yyyy-mm") -> 2025-08 | C447: SHOCKBYTE | D447: 2.5 | E447: Other | F447: {=IFERROR( INDEX(lookup_table!B:B, MATCH(TRUE, ISNUMBER(SEARCH(lookup_table!A:A,C447)), 0) ), "Uncategorized")} -> Subscriptions | G447: Card1
A448: 45896 | B448: =TEXT(A448,"yyyy-mm") -> 2025-08 | C448: SHOCKBYTE | D448: 2 | E448: Other | F448: {=IFERROR( INDEX(lookup_table!B:B, MATCH(TRUE, ISNUMBER(SEARCH(lookup_table!A:A,C448)), 0) ), "Uncategorized")} -> Subscriptions | G448: Card1
A449: 45896 | B449: =TEXT(A449,"yyyy-mm") -> 2025-08 | C449: ARCO | D449: 13.37 | E449: Gas | F449: {=IFERROR( INDEX(lookup_table!B:B, MATCH(TRUE, ISNUMBER(SEARCH(lookup_table!A:A,C449)), 0) ), "Uncategorized")} -> Transportation | G449: Card1
... A627: 45989 | B627: =TEXT(A627,"yyyy-mm") -> 2025-11 | C627: WITHDRAWAL | D627: 50 | E627: Cash & ATM | F627: {=IFERROR( INDEX(lookup_table!B:B, MATCH(TRUE, ISNUMBER(SEARCH(lookup_table!A:A,C627)), 0) ), "Uncategorized")} -> Withdrawal | G627: Bank2
A628: 45990 | B628: =TEXT(A628,"yyyy-mm") -> 2025-11 | C628: COMPASS COFFEE | D628: 5.96 | F628: {=IFERROR( INDEX(lookup_table!B:B, MATCH(TRUE, ISNUMBER(SEARCH(lookup_table!A:A,C628)), 0) ), "Uncategorized")} -> Dining Out | G628: Bank1
A629: 45992 | B629: =TEXT(A629,"yyyy-mm") -> 2025-12 | C629: HUNTINGTON BANKS | D629: 346.3 | F629: {=IFERROR( INDEX(lookup_table!B:B, MATCH(TRUE, ISNUMBER(SEARCH(lookup_table!A:A,C629)), 0) ), "Uncategorized")} -> Bills | G629: Bank1
A630: 45992 | B630: =TEXT(A630,"yyyy-mm") -> 2025-12 | C630: WEST GLACIER MERCANTILE | D630: 14.47 | E630: Merchandise | F630: {=IFERROR( INDEX(lookup_table!B:B, MATCH(TRUE, ISNUMBER(SEARCH(lookup_table!A:A,C630)), 0) ), "Uncategorized")} -> Groceries | G630: Card2
A631: 45992 | B631: =TEXT(A631,"yyyy-mm") -> 2025-12 | C631: FLEET FARM FUEL | D631: 28.35 | E631: Gas | F631: {=IFERROR( INDEX(lookup_table!B:B, MATCH(TRUE, ISNUMBER(SEARCH(lookup_table!A:A,C631)), 0) ), "Uncategorized")} -> Shopping | G631: Card1
A632: 45992 | B632: =TEXT(A632,"yyyy-mm") -> 2025-12 | C632: CONCOURSE HOTEL F&B | D632: 8 | F632: {=IFERROR( INDEX(lookup_table!B:B, MATCH(TRUE, ISNUMBER(SEARCH(lookup_table!A:A,C632)), 0) ), "Uncategorized")} -> Travel | G632: Bank1
A633: 45993 | B633: =TEXT(A633,"yyyy-mm") -> 2025-12 | C633: DAN & LOUIS OYSTER BAR | D633: 43 | E633: Restaurants | F633: {=IFERROR( INDEX(lookup_table!B:B, MATCH(TRUE, ISNUMBER(SEARCH(lookup_table!A:A,C633)), 0) ), "Uncategorized")} -> Dining Out | G633: Card1
A634: 45993 | B634: =TEXT(A634,"yyyy-mm") -> 2025-12 | C634: AUTOZONE | D634: 28.47 | E634: Other | F634: {=IFERROR( INDEX(lookup_table!B:B, MATCH(TRUE, ISNUMBER(SEARCH(lookup_table!A:A,C634)), 0) ), "Uncategorized")} -> Transportation | G634: Card1
A635: 45994 | B635: =TEXT(A635,"yyyy-mm") -> 2025-12 | C635: ACOUSTIC CAFE | D635: 4 | F635: {=IFERROR( INDEX(lookup_table!B:B, MATCH(TRUE, ISNUMBER(SEARCH(lookup_table!A:A,C635)), 0) ), "Uncategorized")} -> Dining Out | G635: Bank1
A636: 45994 | B636: =TEXT(A636,"yyyy-mm") -> 2025-12 | C636: EAU CLAIRE WI CITATION | D636: 33.95 | E636: Other | F636: {=IFERROR( INDEX(lookup_table!B:B, MATCH(TRUE, ISNUMBER(SEARCH(lookup_table!A:A,C636)), 0) ), "Uncategorized")} -> Transportation | G636: Card1
A637: 45997 | B637: =TEXT(A637,"yyyy-mm") -> 2025-12 | C637: MICHELANGELO'S COFFEEHOUSE | D637: 10.85 | E637: Grocery | F637: {=IFERROR( INDEX(lookup_table!B:B, MATCH(TRUE, ISNUMBER(SEARCH(lookup_table!A:A,C637)), 0) ), "Uncategorized")} -> Dining Out | G637: Card1
A638: 45997 | B638: =TEXT(A638,"yyyy-mm") -> 2025-12 | C638: 360TRAINING.COM | D638: 15.77 | F638: {=IFERROR( INDEX(lookup_table!B:B, MATCH(TRUE, ISNUMBER(SEARCH(lookup_table!A:A,C638)), 0) ), "Uncategorized")} -> Subscriptions | G638: Bank1
A639: 45998 | B639: =TEXT(A639,"yyyy-mm") -> 2025-12 | C639: CULVERS | D639: 9.17 | E639: Restaurants | F639: {=IFERROR( INDEX(lookup_table!B:B, MATCH(TRUE, ISNUMBER(SEARCH(lookup_table!A:A,C639)), 0) ), "Uncategorized")} -> Dining Out | G639: Card1
A640: 45998 | B640: =TEXT(A640,"yyyy-mm") -> 2025-12 | C640: CULVERS | D640: 9.7 | E640: Restaurants | F640: {=IFERROR( INDEX(lookup_table!B:B, MATCH(TRUE, ISNUMBER(SEARCH(lookup_table!A:A,C640)), 0) ), "Uncategorized")} -> Dining Out | G640: Card1
A641: 45998 | B641: =TEXT(A641,"yyyy-mm") -> 2025-12 | C641: KWIK TRIP | D641: 31.46 | E641: Gas | F641: {=IFERROR( INDEX(lookup_table!B:B, MATCH(TRUE, ISNUMBER(SEARCH(lookup_table!A:A,C641)), 0) ), "Uncategorized")} -> Transportation | G641: Card1
A642: 45999 | B642: =TEXT(A642,"yyyy-mm") -> 2025-12 | C642: CULVERS | D642: 6.94 | E642: Restaurants | F642: {=IFERROR( INDEX(lookup_table!B:B, MATCH(TRUE, ISNUMBER(SEARCH(lookup_table!A:A,C642)), 0) ), "Uncategorized")} -> Dining Out | G642: Card1
A643: 45999 | B643: =TEXT(A643,"yyyy-mm") -> 2025-12 | C643: CULVERS | D643: 15.38 | E643: Restaurants | F643: {=IFERROR( INDEX(lookup_table!B:B, MATCH(TRUE, ISNUMBER(SEARCH(lookup_table!A:A,C643)), 0) ), "Uncategorized")} -> Dining Out | G643: Card1
A644: 45999 | B644: =TEXT(A644,"yyyy-mm") -> 2025-12 | C644: AXS.COM | D644: 24.98 | E644: Entertainment | F644: {=IFERROR( INDEX(lookup_table!B:B, MATCH(TRUE, ISNUMBER(SEARCH(lookup_table!A:A,C644)), 0) ), "Uncategorized")} -> Entertainment | G644: Card1
A645: 45999 | B645: =TEXT(A645,"yyyy-mm") -> 2025-12 | C645: THE MINNESOTA ORCHESTRA | D645: 21.38 | E645: Grocery | F645: {=IFERROR( INDEX(lookup_table!B:B, MATCH(TRUE, ISNUMBER(SEARCH(lookup_table!A:A,C645)), 0) ), "Uncategorized")} -> Entertainment | G645: Card1
A646: 45999 | B646: =TEXT(A646,"yyyy-mm") -> 2025-12 | C646: NIKE | D646: 0.75 | F646: {=IFERROR( INDEX(lookup_table!B:B, MATCH(TRUE, ISNUMBER(SEARCH(lookup_table!A:A,C646)), 0) ), "Uncategorized")} -> Shopping | G646: Bank1
A647: 46000 | B647: =TEXT(A647,"yyyy-mm") -> 2025-12 | C647: WOODMANS FOOD MARKET | D647: 2.44 | F647: {=IFERROR( INDEX(lookup_table!B:B, MATCH(TRUE, ISNUMBER(SEARCH(lookup_table!A:A,C647)), 0) ), "Uncategorized")} -> Groceries | G647: Bank1
A648: 46000 | B648: =TEXT(A648,"yyyy-mm") -> 2025-12 | C648: DULUTH TRADING CO | D648: 115.52 | E648: Other | F648: {=IFERROR( INDEX(lookup_table!B:B, MATCH(TRUE, ISNUMBER(SEARCH(lookup_table!A:A,C648)), 0) ), "Uncategorized")} -> Shopping | G648: Card1
A649: 46001 | B649: =TEXT(A649,"yyyy-mm") -> 2025-12 | C649: TARGET | D649: 6.1 | F649: {=IFERROR( INDEX(lookup_table!B:B, MATCH(TRUE, ISNUMBER(SEARCH(lookup_table!A:A,C649)), 0) ), "Uncategorized")} -> Groceries | G649: Bank1
A650: 46001 | B650: =TEXT(A650,"yyyy-mm") -> 2025-12 | C650: CHEWY.COM | D650: 52.74 | E650: Other | F650: {=IFERROR( INDEX(lookup_table!B:B, MATCH(TRUE, ISNUMBER(SEARCH(lookup_table!A:A,C650)), 0) ), "Uncategorized")} -> Shopping | G650: Card1
A651: 46004 | B651: =TEXT(A651,"yyyy-mm") -> 2025-12 | C651: ANCORA COFFEE | D651: 1.5 | F651: {=IFERROR( INDEX(lookup_table!B:B, MATCH(TRUE, ISNUMBER(SEARCH(lookup_table!A:A,C651)), 0) ), "Uncategorized")} -> Dining Out | G651: Bank1
A652: 46004 | B652: =TEXT(A652,"yyyy-mm") -> 2025-12 | C652: AUDIBLE | D652: 15.77 | E652: Other | F652: {=IFERROR( INDEX(lookup_table!B:B, MATCH(TRUE, ISNUMBER(SEARCH(lookup_table!A:A,C652)), 0) ), "Uncategorized")} -> Subscriptions | G652: Card1
A653: 46005 | B653: =TEXT(A653,"yyyy-mm") -> 2025-12 | C653: CULVERS | D653: 5.19 | E653: Restaurants | F653: {=IFERROR( INDEX(lookup_table!B:B, MATCH(TRUE, ISNUMBER(SEARCH(lookup_table!A:A,C653)), 0) ), "Uncategorized")} -> Dining Out | G653: Card1
A654: 46005 | B654: =TEXT(A654,"yyyy-mm") -> 2025-12 | C654: TRADER JOES | D654: 8.25 | F654: {=IFERROR( INDEX(lookup_table!B:B, MATCH(TRUE, ISNUMBER(SEARCH(lookup_table!A:A,C654)), 0) ), "Uncategorized")} -> Groceries | G654: Bank1
A655: 46007 | B655: =TEXT(A655,"yyyy-mm") -> 2025-12 | C655: CULVERS | D655: 22.13 | E655: Restaurants | F655: {=IFERROR( INDEX(lookup_table!B:B, MATCH(TRUE, ISNUMBER(SEARCH(lookup_table!A:A,C655)), 0) ), "Uncategorized")} -> Dining Out | G655: Card1
A656: 46007 | B656: =TEXT(A656,"yyyy-mm") -> 2025-12 | C656: GOOGLE ONE | D656: 16.99 | F656: {=IFERROR( INDEX(lookup_table!B:B, MATCH(TRUE, ISNUMBER(SEARCH(lookup_table!A:A,C656)), 0) ), "Uncategorized")} -> Subscriptions | G656: Bank1
A657: 46008 | B657: =TEXT(A657,"yyyy-mm") -> 2025-12 | C657: HUNTINGTON BANKS | D657: 175 | F657: {=IFERROR( INDEX(lookup_table!B:B, MATCH(TRUE, ISNUMBER(SEARCH(lookup_table!A:A,C657)), 0) ), "Uncategorized")} -> Bills | G657: Bank1
A658: 46008 | B658: =TEXT(A658,"yyyy-mm") -> 2025-12 | C658: CULVERS | D658: 11.69 | E658: Restaurants | F658: {=IFERROR( INDEX(lookup_table!B:B, MATCH(TRUE, ISNUMBER(SEARCH(lookup_table!A:A,C658)), 0) ), "Uncategorized")} -> Dining Out | G658: Card1
A659: 46008 | B659: =TEXT(A659,"yyyy-mm") -> 2025-12 | C659: REPTILE RAPTURE | D659: 21.71 | E659: Other | F659: {=IFERROR( INDEX(lookup_table!B:B, MATCH(TRUE, ISNUMBER(SEARCH(lookup_table!A:A,C659)), 0) ), "Uncategorized")} -> Shopping | G659: Card1
A660: 46008 | B660: =TEXT(A660,"yyyy-mm") -> 2025-12 | C660: KWIK TRIP | D660: 27.84 | E660: Gas | F660: {=IFERROR( INDEX(lookup_table!B:B, MATCH(TRUE, ISNUMBER(SEARCH(lookup_table!A:A,C660)), 0) ), "Uncategorized")} -> Transportation | G660: Card1
A661: 46009 | B661: =TEXT(A661,"yyyy-mm") -> 2025-12 | C661: REPTILE RAPTURE | D661: 21.71 | E661: Other | F661: {=IFERROR( INDEX(lookup_table!B:B, MATCH(TRUE, ISNUMBER(SEARCH(lookup_table!A:A,C661)), 0) ), "Uncategorized")} -> Shopping | G661: Card1
A662: 46009 | B662: =TEXT(A662,"yyyy-mm") -> 2025-12 | C662: REMITONLINECOM | D662: 79.54 | E662: Other | F662: {=IFERROR( INDEX(lookup_table!B:B, MATCH(TRUE, ISNUMBER(SEARCH(lookup_table!A:A,C662)), 0) ), "Uncategorized")} -> Transportation | G662: Card1
A663: 46010 | B663: =TEXT(A663,"yyyy-mm") -> 2025-12 | C663: CULVERS | D663: 5.59 | E663: Restaurants | F663: {=IFERROR( INDEX(lookup_table!B:B, MATCH(TRUE, ISNUMBER(SEARCH(lookup_table!A:A,C663)), 0) ), "Uncategorized")} -> Dining Out | G663: Card1
A664: 46010 | B664: =TEXT(A664,"yyyy-mm") -> 2025-12 | C664: NAF NAF GRILL | D664: 7 | E664: Entertainment | F664: {=IFERROR( INDEX(lookup_table!B:B, MATCH(TRUE, ISNUMBER(SEARCH(lookup_table!A:A,C664)), 0) ), "Uncategorized")} -> Dining Out | G664: Card1
A665: 46010 | B665: =TEXT(A665,"yyyy-mm") -> 2025-12 | C665: MPRB PARKING APP | D665: 19.62 | E665: Entertainment | F665: {=IFERROR( INDEX(lookup_table!B:B, MATCH(TRUE, ISNUMBER(SEARCH(lookup_table!A:A,C665)), 0) ), "Uncategorized")} -> Travel | G665: Card1
A666: 46011 | B666: =TEXT(A666,"yyyy-mm") -> 2025-12 | C666: CULVERS | D666: 14.95 | E666: Restaurants | F666: {=IFERROR( INDEX(lookup_table!B:B, MATCH(TRUE, ISNUMBER(SEARCH(lookup_table!A:A,C666)), 0) ), "Uncategorized")} -> Dining Out | G666: Card1
A667: 46011 | B667: =TEXT(A667,"yyyy-mm") -> 2025-12 | C667: KWIK TRIP | D667: 23.69 | E667: Gas | F667: {=IFERROR( INDEX(lookup_table!B:B, MATCH(TRUE, ISNUMBER(SEARCH(lookup_table!A:A,C667)), 0) ), "Uncategorized")} -> Transportation | G667: Card1
A668: 46012 | B668: =TEXT(A668,"yyyy-mm") -> 2025-12 | C668: THE SOAP OPERA | D668: 55.92 | E668: Merchandise | F668: {=IFERROR( INDEX(lookup_table!B:B, MATCH(TRUE, ISNUMBER(SEARCH(lookup_table!A:A,C668)), 0) ), "Uncategorized")} -> Shopping | G668: Card2
A669: 46013 | B669: =TEXT(A669,"yyyy-mm") -> 2025-12 | C669: MCDONALD'S | D669: 3.15 | F669: {=IFERROR( INDEX(lookup_table!B:B, MATCH(TRUE, ISNUMBER(SEARCH(lookup_table!A:A,C669)), 0) ), "Uncategorized")} -> Dining Out | G669: Bank1
A670: 46013 | B670: =TEXT(A670,"yyyy-mm") -> 2025-12 | C670: PARAMOUNT+ | D670: 1 | F670: {=IFERROR( INDEX(lookup_table!B:B, MATCH(TRUE, ISNUMBER(SEARCH(lookup_table!A:A,C670)), 0) ), "Uncategorized")} -> Subscriptions | G670: Bank1
A671: 46013 | B671: =TEXT(A671,"yyyy-mm") -> 2025-12 | C671: KWIK TRIP | D671: 8.1 | E671: Gas | F671: {=IFERROR( INDEX(lookup_table!B:B, MATCH(TRUE, ISNUMBER(SEARCH(lookup_table!A:A,C671)), 0) ), "Uncategorized")} -> Transportation | G671: Card1
A672: 46014 | B672: =TEXT(A672,"yyyy-mm") -> 2025-12 | C672: TACO JOHNS | D672: 11.58 | F672: {=IFERROR( INDEX(lookup_table!B:B, MATCH(TRUE, ISNUMBER(SEARCH(lookup_table!A:A,C672)), 0) ), "Uncategorized")} -> Dining Out | G672: Bank1
A673: 46014 | B673: =TEXT(A673,"yyyy-mm") -> 2025-12 | C673: CITGO GRESHAM MINI M | D673: 42.24 | E673: Gasoline | F673: {=IFERROR( INDEX(lookup_table!B:B, MATCH(TRUE, ISNUMBER(SEARCH(lookup_table!A:A,C673)), 0) ), "Uncategorized")} -> Transportation | G673: Card2
A674: 46015 | B674: =TEXT(A674,"yyyy-mm") -> 2025-12 | C674: WALMART | D674: 11.49 | F674: {=IFERROR( INDEX(lookup_table!B:B, MATCH(TRUE, ISNUMBER(SEARCH(lookup_table!A:A,C674)), 0) ), "Uncategorized")} -> Groceries | G674: Bank1
A675: 46015 | B675: =TEXT(A675,"yyyy-mm") -> 2025-12 | C675: WOODMANS FOOD MARKET | D675: 21.83 | F675: {=IFERROR( INDEX(lookup_table!B:B, MATCH(TRUE, ISNUMBER(SEARCH(lookup_table!A:A,C675)), 0) ), "Uncategorized")} -> Groceries | G675: Bank1
A676: 46015 | B676: =TEXT(A676,"yyyy-mm") -> 2025-12 | C676: FLEET FARM | D676: 11.59 | E676: Other | F676: {=IFERROR( INDEX(lookup_table!B:B, MATCH(TRUE, ISNUMBER(SEARCH(lookup_table!A:A,C676)), 0) ), "Uncategorized")} -> Shopping | G676: Card1
A677: 46015 | B677: =TEXT(A677,"yyyy-mm") -> 2025-12 | C677: FLEET FARM FUEL | D677: 17.36 | E677: Gas | F677: {=IFERROR( INDEX(lookup_table!B:B, MATCH(TRUE, ISNUMBER(SEARCH(lookup_table!A:A,C677)), 0) ), "Uncategorized")} -> Shopping | G677: Card1
A678: 46015 | B678: =TEXT(A678,"yyyy-mm") -> 2025-12 | C678: GOODWILL | D678: 5.24 | F678: {=IFERROR( INDEX(lookup_table!B:B, MATCH(TRUE, ISNUMBER(SEARCH(lookup_table!A:A,C678)), 0) ), "Uncategorized")} -> Shopping | G678: Bank1
A679: 46016 | B679: =TEXT(A679,"yyyy-mm") -> 2025-12 | C679: DUNKIN | D679: 3.94 | F679: {=IFERROR( INDEX(lookup_table!B:B, MATCH(TRUE, ISNUMBER(SEARCH(lookup_table!A:A,C679)), 0) ), "Uncategorized")} -> Dining Out | G679: Bank1
A680: 46016 | B680: =TEXT(A680,"yyyy-mm") -> 2025-12 | C680: PARAMOUNT+ | D680: 4.74 | E680: Utilities | F680: {=IFERROR( INDEX(lookup_table!B:B, MATCH(TRUE, ISNUMBER(SEARCH(lookup_table!A:A,C680)), 0) ), "Uncategorized")} -> Subscriptions | G680: Card1
A681: 46017 | B681: =TEXT(A681,"yyyy-mm") -> 2025-12 | C681: MCDONALD'S | D681: 131.79 | E681: Grocery | F681: {=IFERROR( INDEX(lookup_table!B:B, MATCH(TRUE, ISNUMBER(SEARCH(lookup_table!A:A,C681)), 0) ), "Uncategorized")} -> Dining Out | G681: Card1
A682: 46017 | B682: =TEXT(A682,"yyyy-mm") -> 2025-12 | C682: ALDI | D682: 32.98 | E682: Grocery | F682: {=IFERROR( INDEX(lookup_table!B:B, MATCH(TRUE, ISNUMBER(SEARCH(lookup_table!A:A,C682)), 0) ), "Uncategorized")} -> Groceries | G682: Card1
A683: 46019 | B683: =TEXT(A683,"yyyy-mm") -> 2025-12 | C683: MICHAELS STORES | D683: 10.82 | E683: Grocery | F683: {=IFERROR( INDEX(lookup_table!B:B, MATCH(TRUE, ISNUMBER(SEARCH(lookup_table!A:A,C683)), 0) ), "Uncategorized")} -> Shopping | G683: Card1
A684: 46020 | B684: =TEXT(A684,"yyyy-mm") -> 2025-12 | C684: CHIPOTLE | D684: 9.65 | E684: Restaurants | F684: {=IFERROR( INDEX(lookup_table!B:B, MATCH(TRUE, ISNUMBER(SEARCH(lookup_table!A:A,C684)), 0) ), "Uncategorized")} -> Dining Out | G684: Card1
A685: 46020 | B685: =TEXT(A685,"yyyy-mm") -> 2025-12 | C685: WOODMANS FOOD MARKET | D685: 6.88 | F685: {=IFERROR( INDEX(lookup_table!B:B, MATCH(TRUE, ISNUMBER(SEARCH(lookup_table!A:A,C685)), 0) ), "Uncategorized")} -> Groceries | G685: Bank1
A686: 46020 | B686: =TEXT(A686,"yyyy-mm") -> 2025-12 | C686: FLEET FARM FUEL | D686: 23.95 | E686: Gas | F686: {=IFERROR( INDEX(lookup_table!B:B, MATCH(TRUE, ISNUMBER(SEARCH(lookup_table!A:A,C686)), 0) ), "Uncategorized")} -> Shopping | G686: Card1
A687: 46021 | B687: =TEXT(A687,"yyyy-mm") -> 2025-12 | C687: LOS GEMELOS MEXICAN RESTAURANT | D687: 2.99 | F687: {=IFERROR( INDEX(lookup_table!B:B, MATCH(TRUE, ISNUMBER(SEARCH(lookup_table!A:A,C687)), 0) ), "Uncategorized")} -> Dining Out | G687: Bank1
A688: 46021 | B688: =TEXT(A688,"yyyy-mm") -> 2025-12 | C688: STOP N SHOP | D688: 57.32 | E688: Services | F688: {=IFERROR( INDEX(lookup_table!B:B, MATCH(TRUE, ISNUMBER(SEARCH(lookup_table!A:A,C688)), 0) ), "Uncategorized")} -> Groceries | G688: Card2
A689: 46021 | B689: =TEXT(A689,"yyyy-mm") -> 2025-12 | C689: EAU CLAIRE WI CITATION | D689: 33.95 | E689: Other | F689: {=IFERROR( INDEX(lookup_table!B:B, MATCH(TRUE, ISNUMBER(SEARCH(lookup_table!A:A,C689)), 0) ), "Uncategorized")} -> Transportation | G689: Card1
A690: 46022 | B690: =TEXT(A690,"yyyy-mm") -> 2025-12 | C690: CHIPOTLE | D690: 0.53 | F690: {=IFERROR( INDEX(lookup_table!B:B, MATCH(TRUE, ISNUMBER(SEARCH(lookup_table!A:A,C690)), 0) ), "Uncategorized")} -> Dining Out | G690: Bank1
A691: 46022 | B691: =TEXT(A691,"yyyy-mm") -> 2025-12 | C691: CHIPOTLE | D691: 9.86 | E691: Restaurants | F691: {=IFERROR( INDEX(lookup_table!B:B, MATCH(TRUE, ISNUMBER(SEARCH(lookup_table!A:A,C691)), 0) ), "Uncategorized")} -> Dining Out | G691: Card1
A692: 46024 | B692: =TEXT(A692,"yyyy-mm") -> 2026-01 | C692: FLEET FARM | D692: 12.64 | E692: Other | F692: {=IFERROR( INDEX(lookup_table!B:B, MATCH(TRUE, ISNUMBER(SEARCH(lookup_table!A:A,C692)), 0) ), "Uncategorized")} -> Shopping | G692: Card1
A693: 46024 | B693: =TEXT(A693,"yyyy-mm") -> 2026-01 | C693: KWIK TRIP | D693: 24.15 | E693: Gas | F693: {=IFERROR( INDEX(lookup_table!B:B, MATCH(TRUE, ISNUMBER(SEARCH(lookup_table!A:A,C693)), 0) ), "Uncategorized")} -> Transportation | G693: Card1
A694: 46025 | B694: =TEXT(A694,"yyyy-mm") -> 2026-01 | C694: CARHARTT RETAIL | D694: 44.99 | E694: Shopping | F694: {=IFERROR( INDEX(lookup_table!B:B, MATCH(TRUE, ISNUMBER(SEARCH(lookup_table!A:A,C694)), 0) ), "Uncategorized")} -> Shopping | G694: Card1
A695: 46025 | B695: =TEXT(A695,"yyyy-mm") -> 2026-01 | C695: REPTILE RAPTURE | D695: 18.95 | E695: Other | F695: {=IFERROR( INDEX(lookup_table!B:B, MATCH(TRUE, ISNUMBER(SEARCH(lookup_table!A:A,C695)), 0) ), "Uncategorized")} -> Shopping | G695: Card1
A696: 46027 | B696: =TEXT(A696,"yyyy-mm") -> 2026-01 | C696: W GLACIER SWEET TREATS | D696: 8 | F696: {=IFERROR( INDEX(lookup_table!B:B, MATCH(TRUE, ISNUMBER(SEARCH(lookup_table!A:A,C696)), 0) ), "Uncategorized")} -> Dining Out | G696: Bank1
A697: 46028 | B697: =TEXT(A697,"yyyy-mm") -> 2026-01 | C697: AMERICAN FUNDS | D697: 50 | F697: {=IFERROR( INDEX(lookup_table!B:B, MATCH(TRUE, ISNUMBER(SEARCH(lookup_table!A:A,C697)), 0) ), "Uncategorized")} -> Bills | G697: Bank1
A698: 46028 | B698: =TEXT(A698,"yyyy-mm") -> 2026-01 | C698: CDA CLOTHING CO | D698: 10.77 | E698: Other | F698: {=IFERROR( INDEX(lookup_table!B:B, MATCH(TRUE, ISNUMBER(SEARCH(lookup_table!A:A,C698)), 0) ), "Uncategorized")} -> Shopping | G698: Card1
A699: 46030 | B699: =TEXT(A699,"yyyy-mm") -> 2026-01 | C699: HUNTINGTON BANKS | D699: 346.3 | F699: {=IFERROR( INDEX(lookup_table!B:B, MATCH(TRUE, ISNUMBER(SEARCH(lookup_table!A:A,C699)), 0) ), "Uncategorized")} -> Bills | G699: Bank1
...

Sheet monthly_summary
V1: =IFERROR(__xludf.DUMMYFUNCTION("QUERY(raw_data!B:E, ""select C, sum(D) where C is not null group by C order by sum(D) desc limit 11 label C 'Merchant', sum(D) 'Total Spent'"")"),"Merchant") -> Merchant | W1: =IFERROR(__xludf.DUMMYFUNCTION("""COMPUTED_VALUE"""),"Total Spent") -> Total Spent
V2: =IFERROR(__xludf.DUMMYFUNCTION("""COMPUTED_VALUE"""),"STEVE BROWN APARTMENTS") -> STEVE BROWN APARTMENTS | W2: =IFERROR(__xludf.DUMMYFUNCTION("""COMPUTED_VALUE"""),5235.0) -> 5235
V3: =IFERROR(__xludf.DUMMYFUNCTION("""COMPUTED_VALUE"""),"HUNTINGTON BANKS") -> HUNTINGTON BANKS | W3: =IFERROR(__xludf.DUMMYFUNCTION("""COMPUTED_VALUE"""),4876.9000000000015) -> 4876.9
V4: =IFERROR(__xludf.DUMMYFUNCTION("""COMPUTED_VALUE"""),"MADISON GAS & ELECTRIC") -> MADISON GAS & ELECTRIC | W4: =IFERROR(__xludf.DUMMYFUNCTION("""COMPUTED_VALUE"""),1102.84) -> 1102.84
V5: =IFERROR(__xludf.DUMMYFUNCTION("""COMPUTED_VALUE"""),"KWIK TRIP") -> KWIK TRIP | W5: =IFERROR(__xludf.DUMMYFUNCTION("""COMPUTED_VALUE"""),999.4600000000003) -> 999.46
V6: =IFERROR(__xludf.DUMMYFUNCTION("""COMPUTED_VALUE"""),"GRAHAMS AUTO & TRUCK") -> GRAHAMS AUTO & TRUCK | W6: =IFERROR(__xludf.DUMMYFUNCTION("""COMPUTED_VALUE"""),825.15) -> 825.15
V7: =IFERROR(__xludf.DUMMYFUNCTION("""COMPUTED_VALUE"""),"WOODMANS FOOD MARKET") -> WOODMANS FOOD MARKET | W7: =IFERROR(__xludf.DUMMYFUNCTION("""COMPUTED_VALUE"""),773.5800000000002) -> 773.58
V8: =IFERROR(__xludf.DUMMYFUNCTION("""COMPUTED_VALUE"""),"GAMERS LIBRARY") -> GAMERS LIBRARY | W8: =IFERROR(__xludf.DUMMYFUNCTION("""COMPUTED_VALUE"""),663.1500000000001) -> 663.15
V9: =IFERROR(__xludf.DUMMYFUNCTION("""COMPUTED_VALUE"""),"AMERICAN FUNDS") -> AMERICAN FUNDS | W9: =IFERROR(__xludf.DUMMYFUNCTION("""COMPUTED_VALUE"""),600.0) -> 600
V10: =IFERROR(__xludf.DUMMYFUNCTION("""COMPUTED_VALUE"""),"STATE FARM INSURANCE") -> STATE FARM INSURANCE | W10: =IFERROR(__xludf.DUMMYFUNCTION("""COMPUTED_VALUE"""),487.78000000000003) -> 487.78
V11: =IFERROR(__xludf.DUMMYFUNCTION("""COMPUTED_VALUE"""),"ALDI") -> ALDI | W11: =IFERROR(__xludf.DUMMYFUNCTION("""COMPUTED_VALUE"""),479.89) -> 479.89
V12: =IFERROR(__xludf.DUMMYFUNCTION("""COMPUTED_VALUE"""),"JIFFY LUBE") -> JIFFY LUBE | W12: =IFERROR(__xludf.DUMMYFUNCTION("""COMPUTED_VALUE"""),469.19000000000005) -> 469.19

Sheet lookup_table
A1: Keyword | B1: Category
A2: american funds | B2: Bills
A3: gas & electric | B3: Bills
A4: huntington | B4: Bills
A5: state farm | B5: Bills
A6: steve brown apartments | B6: Bills
A7: usps | B7: Bills
A8: acoustic | B8: Dining Out
A9: brewing | B9: Dining Out
A10: burger | B10: Dining Out
A11: cafe | B11: Dining Out
A12: caribou coffee | B12: Dining Out
... A165: shockbyte | B165: Subscriptions
A166: 76 | B166: Transportation
A167: amanda park | B167: Transportation
A168: amoco | B168: Transportation
A169: arco | B169: Transportation
A170: auto & truck | B170: Transportation
A171: autozone | B171: Transportation
A172: bp | B172: Transportation
A173: casey | B173: Transportation
A174: cc94 | B174: Transportation
A175: cenex | B175: Transportation
A176: chevron | B176: Transportation
A177: circle k | B177: Transportation
A178: citation | B178: Transportation
... A256: withdrawal | B256: Withdrawal

Sheet categories
A1: my_category | B1: description | C1: budget_monthly
A2: Groceries | B2: Supermarkets, food stores | C2: =400 -> 400
A3: Dining Out | B3: Restaurants, bars, coffee | C3: =300 -> 300
A4: Transportation | B4: Gas, Uber, parking, car payment, insurance | C4: =346.6+100+58+200 -> 704.6
A5: Subscriptions | B5: Netflix, Spotify, gym | C5: =30 -> 30
A6: Travel | B6: Doctors, pharmacy, insurance | C6: =0 -> 0
A7: Bills | B7: Rent, utilities, insurance | C7: =595+25+30+60+7.75 -> 717.75
A8: Entertainment | B8: Movies, concerts, hobbies | C8: =200 -> 200
A9: Shopping | B9: Clothing, Amazon, misc | C9: =100 -> 100
A10: Withdrawl | B10: ATM | C10: ---
A11: Other | B11: Everything else | C11: =100 -> 100

Sheet dashboard
